hanzo_tools/__init__.py
hanzo_tools/editor/__init__.py
hanzo_tools/editor/neovim_command.py
hanzo_tools/editor/neovim_edit.py
hanzo_tools/editor/neovim_session.py
hanzo_tools_editor-0.2.0.dist-info/METADATA
hanzo_tools_editor-0.2.0.dist-info/WHEEL
hanzo_tools_editor-0.2.0.dist-info/entry_points.txt
hanzo_tools_editor-0.2.0.dist-info/top_level.txt
hanzo_tools_editor-0.2.0.dist-info/RECORD
