Metadata-Version: 2.4
Name: hanzo-tools-editor
Version: 0.2.0
Summary: Editor integration tools for Hanzo AI - Neovim, VSCode, etc.
Author-email: Hanzo Industries Inc <dev@hanzo.ai>
License: MIT
Project-URL: Homepage, https://github.com/hanzoai/python-sdk
Keywords: hanzo,tools,editor,neovim,vscode,mcp,ai
Classifier: Programming Language :: Python :: 3
Classifier: License :: OSI Approved :: MIT License
Classifier: Operating System :: OS Independent
Requires-Python: >=3.12
Requires-Dist: hanzo-tools-core>=0.1.0
Requires-Dist: mcp>=1.25.0
Requires-Dist: fastmcp>=2.14.1
Requires-Dist: pydantic>=2.12.5
Provides-Extra: neovim
Requires-Dist: pynvim>=0.5.0; extra == "neovim"
Provides-Extra: dev
Requires-Dist: pytest>=7.0.0; extra == "dev"
Requires-Dist: ruff>=0.14.0; extra == "dev"
